[
  {
    "jid": "6285600793871@s.whatsapp.net",
    "db": [
      {
        "nama": "#menu",
        "count": 102
      },
      {
        "nama": "#sticker",
        "count": 69
      },
      {
        "nama": "#tes",
        "count": 196
      },
      {
        "nama": "#runtime",
        "count": 13
      },
      {
        "nama": "#autoaijapri",
        "count": 11
      },
      {
        "nama": "#listpremium",
        "count": 11
      },
      {
        "nama": "#toimage",
        "count": 10
      },
      {
        "nama": "#attp",
        "count": 7
      },
      {
        "nama": "#speed",
        "count": 3
      },
      {
        "nama": "#addprem",
        "count": 5
      },
      {
        "nama": "#nowa",
        "count": 4
      },
      {
        "nama": "#foliokiri",
        "count": 2
      },
      {
        "nama": "#cekpremium",
        "count": 2
      },
      {
        "nama": "#stickerwm",
        "count": 17
      },
      {
        "nama": "#infobot",
        "count": 2
      },
      {
        "nama": "#dashboard",
        "count": 2
      },
      {
        "nama": "#say",
        "count": 2
      },
      {
        "nama": "#nulis",
        "count": 2
      },
      {
        "nama": "#nuliskiri",
        "count": 1
      },
      {
        "nama": "#delprem",
        "count": 2
      },
      {
        "nama": "#tovideo",
        "count": 1
      },
      {
        "nama": "#tiktok",
        "count": 5
      },
      {
        "nama": "#cecan",
        "count": 5
      },
      {
        "nama": "#antiwame",
        "count": 1
      },
      {
        "nama": "#welcome",
        "count": 6
      },
      {
        "nama": "#lirik",
        "count": 2
      },
      {
        "nama": "#qc",
        "count": 26
      },
      {
        "nama": "#group",
        "count": 9
      },
      {
        "nama": "#close",
        "count": 1
      },
      {
        "nama": "#tomp3",
        "count": 2
      },
      {
        "nama": "#smeme",
        "count": 10
      },
      {
        "nama": "#cogan",
        "count": 1
      },
      {
        "nama": "#waifu",
        "count": 1
      },
      {
        "nama": "#resetlimit",
        "count": 2
      },
      {
        "nama": "#afk",
        "count": 14
      },
      {
        "nama": "#grupwa",
        "count": 2
      },
      {
        "nama": "#wanted",
        "count": 3
      },
      {
        "nama": "#antilink",
        "count": 3
      },
      {
        "nama": "#simih",
        "count": 1
      },
      {
        "nama": "#antionce",
        "count": 2
      },
      {
        "nama": "#antidelete",
        "count": 5
      },
      {
        "nama": "#antibugsetting",
        "count": 4
      },
      {
        "nama": "#kickme",
        "count": 8
      },
      {
        "nama": "#left",
        "count": 2
      },
      {
        "nama": "#revoke",
        "count": 1
      },
      {
        "nama": "#autoaigrup",
        "count": 2
      },
      {
        "nama": "#fitnah",
        "count": 1
      },
      {
        "nama": "#emojimix",
        "count": 1
      },
      {
        "nama": "#setwelcome",
        "count": 1
      },
      {
        "nama": "#delsetwelcome",
        "count": 1
      },
      {
        "nama": "#tai",
        "count": 6
      }
    ]
  },
  {
    "jid": "6285742858312@s.whatsapp.net",
    "db": [
      {
        "nama": "#menu",
        "count": 2
      }
    ]
  },
  {
    "jid": "6289508644702@s.whatsapp.net",
    "db": [
      {
        "nama": "#tiktok",
        "count": 21
      },
      {
        "nama": "#say",
        "count": 1
      }
    ]
  },
  {
    "jid": "6285727341138@s.whatsapp.net",
    "db": [
      {
        "nama": "#sticker",
        "count": 3
      }
    ]
  },
  {
    "jid": "6285741759235@s.whatsapp.net",
    "db": [
      {
        "nama": "#sticker",
        "count": 3
      },
      {
        "nama": "#menu",
        "count": 2
      },
      {
        "nama": "#tiktok",
        "count": 15
      }
    ]
  },
  {
    "jid": "6283876395282@s.whatsapp.net",
    "db": [
      {
        "nama": "#tiktok",
        "count": 13
      },
      {
        "nama": "#menu",
        "count": 10
      },
      {
        "nama": "#sticker",
        "count": 1
      },
      {
        "nama": "#listbahasa",
        "count": 1
      },
      {
        "nama": "#grupwa",
        "count": 2
      },
      {
        "nama": "#lirik",
        "count": 1
      },
      {
        "nama": "#foliokanan",
        "count": 1
      }
    ]
  },
  {
    "jid": "62895415497664@s.whatsapp.net",
    "db": [
      {
        "nama": "#menu",
        "count": 6
      },
      {
        "nama": "#dashboard",
        "count": 1
      },
      {
        "nama": "#attp",
        "count": 1
      },
      {
        "nama": "#infobot",
        "count": 1
      },
      {
        "nama": "#listpremium",
        "count": 1
      },
      {
        "nama": "#sticker",
        "count": 1
      },
      {
        "nama": "#tes",
        "count": 15
      }
    ]
  },
  {
    "jid": "6285727631507@s.whatsapp.net",
    "db": [
      {
        "nama": "#menu",
        "count": 26
      },
      {
        "nama": "#tiktok",
        "count": 7
      },
      {
        "nama": "#antilink",
        "count": 4
      },
      {
        "nama": "#resetlimit",
        "count": 1
      },
      {
        "nama": "#sticker",
        "count": 24
      },
      {
        "nama": "#addprem",
        "count": 8
      },
      {
        "nama": "#listpremium",
        "count": 9
      },
      {
        "nama": "#delprem",
        "count": 4
      },
      {
        "nama": "#tes",
        "count": 21
      },
      {
        "nama": "#smeme",
        "count": 12
      },
      {
        "nama": "#stickerwm",
        "count": 8
      },
      {
        "nama": "#lirik",
        "count": 2
      },
      {
        "nama": "#toimage",
        "count": 3
      },
      {
        "nama": "#tovid",
        "count": 1
      },
      {
        "nama": "#antiwame",
        "count": 2
      },
      {
        "nama": "#antilink2",
        "count": 2
      },
      {
        "nama": "#antiwame2",
        "count": 1
      },
      {
        "nama": "#cecan",
        "count": 1
      },
      {
        "nama": "#grupwa",
        "count": 2
      },
      {
        "nama": "#emojimix",
        "count": 5
      },
      {
        "nama": "#welcome",
        "count": 1
      },
      {
        "nama": "#attp",
        "count": 2
      },
      {
        "nama": "#afk",
        "count": 1
      },
      {
        "nama": "#donate",
        "count": 2
      }
    ]
  },
  {
    "jid": "6281546863465@s.whatsapp.net",
    "db": [
      {
        "nama": "#menu",
        "count": 1
      }
    ]
  },
  {
    "jid": "6287798647593@s.whatsapp.net",
    "db": [
      {
        "nama": "#menu",
        "count": 3
      },
      {
        "nama": "#cogan",
        "count": 1
      },
      {
        "nama": "#tiktok",
        "count": 2
      },
      {
        "nama": "#afk",
        "count": 3
      }
    ]
  },
  {
    "jid": "6281539258636@s.whatsapp.net",
    "db": [
      {
        "nama": "#sticker",
        "count": 3
      }
    ]
  },
  {
    "jid": "6285700871480@s.whatsapp.net",
    "db": [
      {
        "nama": "#menu",
        "count": 2
      },
      {
        "nama": "#cecan",
        "count": 1
      },
      {
        "nama": "#cogan",
        "count": 1
      }
    ]
  },
  {
    "jid": "6281944636729@s.whatsapp.net",
    "db": [
      {
        "nama": "#menu",
        "count": 10
      },
      {
        "nama": "#infobot",
        "count": 1
      },
      {
        "nama": "#lirik",
        "count": 9
      },
      {
        "nama": "#grupwa",
        "count": 6
      },
      {
        "nama": "#tiktok",
        "count": 1
      }
    ]
  },
  {
    "jid": "6289689569971@s.whatsapp.net",
    "db": [
      {
        "nama": "#menu",
        "count": 3
      },
      {
        "nama": "#sticker",
        "count": 2
      },
      {
        "nama": "#smeme",
        "count": 4
      },
      {
        "nama": "#afk",
        "count": 1
      }
    ]
  },
  {
    "jid": "6282328687712@s.whatsapp.net",
    "db": [
      {
        "nama": "#menu",
        "count": 12
      },
      {
        "nama": "#sticker",
        "count": 3
      },
      {
        "nama": "#smeme",
        "count": 5
      },
      {
        "nama": "#cecan",
        "count": 1
      },
      {
        "nama": "#afk",
        "count": 12
      },
      {
        "nama": "#waifu",
        "count": 1
      }
    ]
  },
  {
    "jid": "6282133807375@s.whatsapp.net",
    "db": [
      {
        "nama": "#menu",
        "count": 1
      },
      {
        "nama": "#afk",
        "count": 1
      }
    ]
  },
  {
    "jid": "6289612541686@s.whatsapp.net",
    "db": [
      {
        "nama": "#menu",
        "count": 2
      },
      {
        "nama": "#sticker",
        "count": 8
      }
    ]
  },
  {
    "jid": "6285859709552@s.whatsapp.net",
    "db": [
      {
        "nama": "#menu",
        "count": 2
      },
      {
        "nama": "#sticker",
        "count": 31
      }
    ]
  },
  {
    "jid": "6287855793074@s.whatsapp.net",
    "db": [
      {
        "nama": "#sticker",
        "count": 32
      },
      {
        "nama": "#menu",
        "count": 1
      },
      {
        "nama": "#smeme",
        "count": 1
      }
    ]
  },
  {
    "jid": "6283195749042@s.whatsapp.net",
    "db": [
      {
        "nama": "#menu",
        "count": 2
      }
    ]
  },
  {
    "jid": "6285779604705@s.whatsapp.net",
    "db": [
      {
        "nama": "#afk",
        "count": 11
      },
      {
        "nama": "#menu",
        "count": 10
      },
      {
        "nama": "#tiktok",
        "count": 4
      },
      {
        "nama": "#sticker",
        "count": 8
      },
      {
        "nama": "#stickerwm",
        "count": 7
      }
    ]
  },
  {
    "jid": "6283116764135@s.whatsapp.net",
    "db": [
      {
        "nama": "#menu",
        "count": 5
      },
      {
        "nama": "#smeme",
        "count": 1
      },
      {
        "nama": "#sticker",
        "count": 16
      },
      {
        "nama": "#afk",
        "count": 3
      }
    ]
  },
  {
    "jid": "6282118484275@s.whatsapp.net",
    "db": [
      {
        "nama": "#afk",
        "count": 2
      }
    ]
  },
  {
    "jid": "6281262290573@s.whatsapp.net",
    "db": [
      {
        "nama": "#sticker",
        "count": 1
      }
    ]
  },
  {
    "jid": "6282111785203@s.whatsapp.net",
    "db": [
      {
        "nama": "#afk",
        "count": 4
      }
    ]
  },
  {
    "jid": "6281262339320@s.whatsapp.net",
    "db": [
      {
        "nama": "#afk",
        "count": 47
      },
      {
        "nama": "#menu",
        "count": 10
      },
      {
        "nama": "#sticker",
        "count": 2
      },
      {
        "nama": "#stickerwm",
        "count": 42
      },
      {
        "nama": "#cekpremium",
        "count": 1
      },
      {
        "nama": "#listpremium",
        "count": 2
      },
      {
        "nama": "#tomp3",
        "count": 1
      },
      {
        "nama": "#waifu",
        "count": 4
      },
      {
        "nama": "#grupwa",
        "count": 1
      },
      {
        "nama": "#infobot",
        "count": 1
      },
      {
        "nama": "#emojimix",
        "count": 5
      },
      {
        "nama": "#say",
        "count": 2
      },
      {
        "nama": "#attp",
        "count": 4
      },
      {
        "nama": "#cekdrive",
        "count": 1
      }
    ]
  },
  {
    "jid": "6283898966833@s.whatsapp.net",
    "db": [
      {
        "nama": "#menu",
        "count": 7
      },
      {
        "nama": "#afk",
        "count": 5
      },
      {
        "nama": "#sticker",
        "count": 9
      },
      {
        "nama": "#tes",
        "count": 6
      }
    ]
  },
  {
    "jid": "6285707723690@s.whatsapp.net",
    "db": [
      {
        "nama": "#sticker",
        "count": 8
      }
    ]
  },
  {
    "jid": "6283897092631@s.whatsapp.net",
    "db": [
      {
        "nama": "#menu",
        "count": 1
      }
    ]
  },
  {
    "jid": "6282281247751@s.whatsapp.net",
    "db": [
      {
        "nama": "#menu",
        "count": 3
      },
      {
        "nama": "#sticker",
        "count": 2
      },
      {
        "nama": "#afk",
        "count": 1
      }
    ]
  },
  {
    "jid": "6283853066350@s.whatsapp.net",
    "db": [
      {
        "nama": "#menu",
        "count": 1
      }
    ]
  },
  {
    "jid": "62895411238610@s.whatsapp.net",
    "db": [
      {
        "nama": "#afk",
        "count": 1
      }
    ]
  },
  {
    "jid": "6288232739101@s.whatsapp.net",
    "db": [
      {
        "nama": "#afk",
        "count": 4
      }
    ]
  },
  {
    "jid": "6285859458975@s.whatsapp.net",
    "db": [
      {
        "nama": "#afk",
        "count": 2
      }
    ]
  },
  {
    "jid": "6287765444211@s.whatsapp.net",
    "db": [
      {
        "nama": "#menu",
        "count": 1
      }
    ]
  },
  {
    "jid": "6281223031432@s.whatsapp.net",
    "db": [
      {
        "nama": "#afk",
        "count": 3
      },
      {
        "nama": "#menu",
        "count": 1
      }
    ]
  },
  {
    "jid": "6285716011909@s.whatsapp.net",
    "db": [
      {
        "nama": "#menu",
        "count": 1
      }
    ]
  },
  {
    "jid": "6287771177240@s.whatsapp.net",
    "db": [
      {
        "nama": "#menu",
        "count": 1
      }
    ]
  },
  {
    "jid": "6285817698354@s.whatsapp.net",
    "db": [
      {
        "nama": "#menu",
        "count": 2
      }
    ]
  },
  {
    "jid": "6289614707966@s.whatsapp.net",
    "db": [
      {
        "nama": "#menu",
        "count": 1
      },
      {
        "nama": "#sticker",
        "count": 6
      }
    ]
  },
  {
    "jid": "6282162027730@s.whatsapp.net",
    "db": [
      {
        "nama": "#menu",
        "count": 4
      },
      {
        "nama": "#sticker",
        "count": 6
      }
    ]
  },
  {
    "jid": "6282280719600@s.whatsapp.net",
    "db": [
      {
        "nama": "#menu",
        "count": 2
      }
    ]
  },
  {
    "jid": "6285854943909@s.whatsapp.net",
    "db": [
      {
        "nama": "#menu",
        "count": 1
      }
    ]
  },
  {
    "jid": "6285607655543@s.whatsapp.net",
    "db": [
      {
        "nama": "#sticker",
        "count": 1
      },
      {
        "nama": "#menu",
        "count": 1
      }
    ]
  },
  {
    "jid": "6283165951907@s.whatsapp.net",
    "db": [
      {
        "nama": "#menu",
        "count": 2
      }
    ]
  },
  {
    "jid": "6283876016720@s.whatsapp.net",
    "db": [
      {
        "nama": "#menu",
        "count": 1
      },
      {
        "nama": "#sticker",
        "count": 2
      }
    ]
  },
  {
    "jid": "6285641384322@s.whatsapp.net",
    "db": [
      {
        "nama": "#menu",
        "count": 2
      }
    ]
  },
  {
    "jid": "6288220252231@s.whatsapp.net",
    "db": [
      {
        "nama": "#menu",
        "count": 3
      }
    ]
  },
  {
    "jid": "6285156038171@s.whatsapp.net",
    "db": [
      {
        "nama": "#menu",
        "count": 1
      }
    ]
  },
  {
    "jid": "6285717510415@s.whatsapp.net",
    "db": [
      {
        "nama": "#menu",
        "count": 2
      }
    ]
  },
  {
    "jid": "62895327044844@s.whatsapp.net",
    "db": [
      {
        "nama": "#menu",
        "count": 1
      }
    ]
  },
  {
    "jid": "62895424449240@s.whatsapp.net",
    "db": [
      {
        "nama": "#menu",
        "count": 2
      },
      {
        "nama": "#sticker",
        "count": 3
      },
      {
        "nama": "#stickerwm",
        "count": 2
      },
      {
        "nama": "#smeme",
        "count": 1
      },
      {
        "nama": "#lirik",
        "count": 6
      }
    ]
  },
  {
    "jid": "6289525258900@s.whatsapp.net",
    "db": [
      {
        "nama": "#menu",
        "count": 1
      },
      {
        "nama": "#sticker",
        "count": 1
      }
    ]
  },
  {
    "jid": "6285725929945@s.whatsapp.net",
    "db": [
      {
        "nama": "#menu",
        "count": 2
      },
      {
        "nama": "#sticker",
        "count": 6
      }
    ]
  },
  {
    "jid": "6285967093164@s.whatsapp.net",
    "db": [
      {
        "nama": "#menu",
        "count": 1
      }
    ]
  },
  {
    "jid": "6283142249490@s.whatsapp.net",
    "db": [
      {
        "nama": "#menu",
        "count": 2
      },
      {
        "nama": "#sticker",
        "count": 5
      }
    ]
  },
  {
    "jid": "6285609288348@s.whatsapp.net",
    "db": [
      {
        "nama": "#menu",
        "count": 1
      },
      {
        "nama": "#sticker",
        "count": 2
      }
    ]
  },
  {
    "jid": "62895426585280@s.whatsapp.net",
    "db": [
      {
        "nama": "#sticker",
        "count": 2
      }
    ]
  },
  {
    "jid": "6285757635545@s.whatsapp.net",
    "db": [
      {
        "nama": "#menu",
        "count": 1
      }
    ]
  },
  {
    "jid": "6285878216777@s.whatsapp.net",
    "db": [
      {
        "nama": "#menu",
        "count": 1
      },
      {
        "nama": "#stickerwm",
        "count": 1
      },
      {
        "nama": "#sticker",
        "count": 1
      }
    ]
  },
  {
    "jid": "6282216456014@s.whatsapp.net",
    "db": [
      {
        "nama": "#menu",
        "count": 2
      }
    ]
  },
  {
    "jid": "6282129492963@s.whatsapp.net",
    "db": [
      {
        "nama": "#menu",
        "count": 1
      },
      {
        "nama": "#sticker",
        "count": 4
      }
    ]
  },
  {
    "jid": "6282134690385@s.whatsapp.net",
    "db": [
      {
        "nama": "#menu",
        "count": 1
      },
      {
        "nama": "#sticker",
        "count": 1
      }
    ]
  },
  {
    "jid": "6282181896994@s.whatsapp.net",
    "db": [
      {
        "nama": "#menu",
        "count": 3
      },
      {
        "nama": "#sticker",
        "count": 3
      }
    ]
  },
  {
    "jid": "6285926313073@s.whatsapp.net",
    "db": [
      {
        "nama": "#menu",
        "count": 1
      }
    ]
  },
  {
    "jid": "6287835110323@s.whatsapp.net",
    "db": [
      {
        "nama": "#menu",
        "count": 1
      }
    ]
  },
  {
    "jid": "6285381551977@s.whatsapp.net",
    "db": [
      {
        "nama": "#sticker",
        "count": 1
      }
    ]
  },
  {
    "jid": "6282217010291@s.whatsapp.net",
    "db": [
      {
        "nama": "#menu",
        "count": 1
      },
      {
        "nama": "#sticker",
        "count": 10
      }
    ]
  },
  {
    "jid": "6289515875244@s.whatsapp.net",
    "db": [
      {
        "nama": "#menu",
        "count": 1
      }
    ]
  },
  {
    "jid": "6285656064294@s.whatsapp.net",
    "db": [
      {
        "nama": "#sticker",
        "count": 1
      },
      {
        "nama": "#menu",
        "count": 1
      }
    ]
  },
  {
    "jid": "6288224656759@s.whatsapp.net",
    "db": [
      {
        "nama": "#menu",
        "count": 1
      }
    ]
  },
  {
    "jid": "62882001361812@s.whatsapp.net",
    "db": [
      {
        "nama": "#sticker",
        "count": 3
      }
    ]
  },
  {
    "jid": "6289514212930@s.whatsapp.net",
    "db": [
      {
        "nama": "#menu",
        "count": 1
      },
      {
        "nama": "#sticker",
        "count": 2
      }
    ]
  },
  {
    "jid": "6283808644418@s.whatsapp.net",
    "db": [
      {
        "nama": "#menu",
        "count": 1
      },
      {
        "nama": "#smeme",
        "count": 1
      }
    ]
  },
  {
    "jid": "6285784460973@s.whatsapp.net",
    "db": [
      {
        "nama": "#menu",
        "count": 2
      }
    ]
  },
  {
    "jid": "6285733028117@s.whatsapp.net",
    "db": [
      {
        "nama": "#sticker",
        "count": 5
      }
    ]
  },
  {
    "jid": "6285161126317@s.whatsapp.net",
    "db": [
      {
        "nama": "#menu",
        "count": 44
      },
      {
        "nama": "#close",
        "count": 30
      },
      {
        "nama": "#cekdrive",
        "count": 1
      },
      {
        "nama": "#addprem",
        "count": 15
      },
      {
        "nama": "#antidelete",
        "count": 6
      },
      {
        "nama": "#tes",
        "count": 185
      },
      {
        "nama": "#antilink",
        "count": 10
      },
      {
        "nama": "#antionce",
        "count": 2
      },
      {
        "nama": "#smeme",
        "count": 4
      },
      {
        "nama": "#sticker",
        "count": 47
      },
      {
        "nama": "#afk",
        "count": 27
      },
      {
        "nama": "#group",
        "count": 30
      },
      {
        "nama": "#lirik",
        "count": 2
      },
      {
        "nama": "#islammenu",
        "count": 1
      },
      {
        "nama": "#allmenu",
        "count": 4
      },
      {
        "nama": "#gamemenu",
        "count": 1
      },
      {
        "nama": "#rpgmenu",
        "count": 1
      },
      {
        "nama": "#toimage",
        "count": 5
      },
      {
        "nama": "#ownermenu",
        "count": 2
      },
      {
        "nama": "#waifu",
        "count": 2
      },
      {
        "nama": "#cekpremium",
        "count": 1
      },
      {
        "nama": "#mute",
        "count": 22
      },
      {
        "nama": "#autoaigrup",
        "count": 5
      },
      {
        "nama": "#addsewa",
        "count": 5
      },
      {
        "nama": "#listpremium",
        "count": 7
      },
      {
        "nama": "#listsewa",
        "count": 4
      },
      {
        "nama": "#delprem",
        "count": 2
      },
      {
        "nama": "#resetlimit",
        "count": 4
      },
      {
        "nama": "#tovn",
        "count": 3
      },
      {
        "nama": "#say",
        "count": 1
      },
      {
        "nama": "#groupmenu",
        "count": 1
      },
      {
        "nama": "#storemenu",
        "count": 2
      },
      {
        "nama": "#tomp3",
        "count": 3
      },
      {
        "nama": "#downloadmenu",
        "count": 3
      },
      {
        "nama": "#mainmenu",
        "count": 1
      },
      {
        "nama": "#casino",
        "count": 9
      },
      {
        "nama": "#nikah",
        "count": 9
      },
      {
        "nama": "#stickerwm",
        "count": 1
      },
      {
        "nama": "#donate",
        "count": 1
      },
      {
        "nama": "#mediafire",
        "count": 3
      }
    ]
  },
  {
    "jid": "6285182913498@s.whatsapp.net",
    "db": [
      {
        "nama": "#sticker",
        "count": 15
      },
      {
        "nama": "#menu",
        "count": 1
      },
      {
        "nama": "#groupmenu",
        "count": 1
      },
      {
        "nama": "#tes",
        "count": 27
      },
      {
        "nama": "#allmenu",
        "count": 12
      },
      {
        "nama": "#group",
        "count": 3
      },
      {
        "nama": "#smeme",
        "count": 6
      },
      {
        "nama": "#stickerwm",
        "count": 3
      },
      {
        "nama": "#afk",
        "count": 13
      },
      {
        "nama": "#lirik",
        "count": 7
      },
      {
        "nama": "#antidelete",
        "count": 2
      },
      {
        "nama": "#close",
        "count": 4
      },
      {
        "nama": "#mute",
        "count": 1
      },
      {
        "nama": "#cekpremium",
        "count": 1
      },
      {
        "nama": "#addprem",
        "count": 1
      },
      {
        "nama": "#emojimix",
        "count": 1
      },
      {
        "nama": "#casino",
        "count": 1
      }
    ]
  },
  {
    "jid": "6281999138024@s.whatsapp.net",
    "db": [
      {
        "nama": "#tes",
        "count": 14
      },
      {
        "nama": "#menu",
        "count": 15
      },
      {
        "nama": "#listpremium",
        "count": 5
      },
      {
        "nama": "#afk",
        "count": 32
      },
      {
        "nama": "#say",
        "count": 23
      },
      {
        "nama": "#voicechanger",
        "count": 3
      },
      {
        "nama": "#transfer",
        "count": 14
      },
      {
        "nama": "#sticker",
        "count": 16
      },
      {
        "nama": "#smeme",
        "count": 24
      },
      {
        "nama": "#buylimit",
        "count": 9
      },
      {
        "nama": "#toimage",
        "count": 15
      },
      {
        "nama": "#randomanime",
        "count": 1
      },
      {
        "nama": "#lirik",
        "count": 6
      },
      {
        "nama": "#cekpremium",
        "count": 1
      },
      {
        "nama": "#emojimix",
        "count": 9
      },
      {
        "nama": "#allmenu",
        "count": 8
      },
      {
        "nama": "#attp",
        "count": 1
      },
      {
        "nama": "#tomp3",
        "count": 2
      },
      {
        "nama": "#tovn",
        "count": 3
      },
      {
        "nama": "#stickerwm",
        "count": 2
      },
      {
        "nama": "#nikah",
        "count": 3
      }
    ]
  },
  {
    "jid": "6282219390496@s.whatsapp.net",
    "db": [
      {
        "nama": "#tes",
        "count": 17
      },
      {
        "nama": "#stickerwm",
        "count": 3
      },
      {
        "nama": "#afk",
        "count": 21
      },
      {
        "nama": "#welcome",
        "count": 1
      },
      {
        "nama": "#sticker",
        "count": 17
      },
      {
        "nama": "#funmenu",
        "count": 1
      },
      {
        "nama": "#toimage",
        "count": 21
      },
      {
        "nama": "#smeme",
        "count": 4
      },
      {
        "nama": "#emojimix",
        "count": 4
      },
      {
        "nama": "#antidelete",
        "count": 1
      },
      {
        "nama": "#mute",
        "count": 4
      },
      {
        "nama": "#group",
        "count": 1
      },
      {
        "nama": "#menu",
        "count": 3
      },
      {
        "nama": "#groupmenu",
        "count": 1
      },
      {
        "nama": "#listpremium",
        "count": 1
      },
      {
        "nama": "#lirik",
        "count": 1
      },
      {
        "nama": "#nikah",
        "count": 1
      }
    ]
  },
  {
    "jid": "6287769350440@s.whatsapp.net",
    "db": [
      {
        "nama": "#sticker",
        "count": 4
      },
      {
        "nama": "#smeme",
        "count": 8
      },
      {
        "nama": "#afk",
        "count": 39
      },
      {
        "nama": "#transfer",
        "count": 6
      },
      {
        "nama": "#buylimit",
        "count": 4
      },
      {
        "nama": "#menu",
        "count": 5
      },
      {
        "nama": "#toimage",
        "count": 3
      },
      {
        "nama": "#tes",
        "count": 6
      },
      {
        "nama": "#say",
        "count": 1
      },
      {
        "nama": "#allmenu",
        "count": 17
      },
      {
        "nama": "#buygamelimit",
        "count": 1
      },
      {
        "nama": "#emojimix",
        "count": 11
      },
      {
        "nama": "#waifu",
        "count": 1
      },
      {
        "nama": "#cogan",
        "count": 1
      }
    ]
  },
  {
    "jid": "6282255256531@s.whatsapp.net",
    "db": [
      {
        "nama": "#smeme",
        "count": 12
      },
      {
        "nama": "#afk",
        "count": 59
      },
      {
        "nama": "#allmenu",
        "count": 5
      },
      {
        "nama": "#emojimix",
        "count": 12
      },
      {
        "nama": "#tes",
        "count": 1
      },
      {
        "nama": "#menu",
        "count": 5
      },
      {
        "nama": "#sticker",
        "count": 22
      },
      {
        "nama": "#transfer",
        "count": 23
      },
      {
        "nama": "#say",
        "count": 2
      },
      {
        "nama": "#casino",
        "count": 3
      },
      {
        "nama": "#downloadmenu",
        "count": 1
      },
      {
        "nama": "#buylimit",
        "count": 2
      },
      {
        "nama": "#listpremium",
        "count": 3
      }
    ]
  },
  {
    "jid": "6283891278026@s.whatsapp.net",
    "db": [
      {
        "nama": "#menu",
        "count": 1
      }
    ]
  },
  {
    "jid": "6282128660045@s.whatsapp.net",
    "db": [
      {
        "nama": "#tomp3",
        "count": 7
      },
      {
        "nama": "#sticker",
        "count": 7
      },
      {
        "nama": "#allmenu",
        "count": 3
      },
      {
        "nama": "#afk",
        "count": 1
      },
      {
        "nama": "#buylimit",
        "count": 7
      },
      {
        "nama": "#menu",
        "count": 4
      }
    ]
  },
  {
    "jid": "6288245428477@s.whatsapp.net",
    "db": [
      {
        "nama": "#menu",
        "count": 1
      },
      {
        "nama": "#randomsticker",
        "count": 1
      },
      {
        "nama": "#sticker",
        "count": 2
      }
    ]
  },
  {
    "jid": "6285795432639@s.whatsapp.net",
    "db": [
      {
        "nama": "#afk",
        "count": 3
      },
      {
        "nama": "#menu",
        "count": 2
      }
    ]
  },
  {
    "jid": "6283866958194@s.whatsapp.net",
    "db": [
      {
        "nama": "#allmenu",
        "count": 3
      },
      {
        "nama": "#waifu",
        "count": 1
      },
      {
        "nama": "#toimage",
        "count": 8
      },
      {
        "nama": "#smeme",
        "count": 19
      },
      {
        "nama": "#sticker",
        "count": 16
      },
      {
        "nama": "#emojimix",
        "count": 20
      },
      {
        "nama": "#buylimit",
        "count": 36
      },
      {
        "nama": "#afk",
        "count": 3
      },
      {
        "nama": "#menu",
        "count": 8
      },
      {
        "nama": "#transfer",
        "count": 3
      },
      {
        "nama": "#downloadmenu",
        "count": 2
      },
      {
        "nama": "#tes",
        "count": 2
      },
      {
        "nama": "#rpgmenu",
        "count": 2
      },
      {
        "nama": "#tomp3",
        "count": 1
      },
      {
        "nama": "#nikah",
        "count": 3
      }
    ]
  },
  {
    "jid": "6285824897088@s.whatsapp.net",
    "db": [
      {
        "nama": "#tes",
        "count": 89
      },
      {
        "nama": "#allmenu",
        "count": 17
      },
      {
        "nama": "#afk",
        "count": 26
      },
      {
        "nama": "#emojimix",
        "count": 13
      },
      {
        "nama": "#toimage",
        "count": 14
      },
      {
        "nama": "#smeme",
        "count": 19
      },
      {
        "nama": "#waifu",
        "count": 5
      },
      {
        "nama": "#stickerwm",
        "count": 70
      },
      {
        "nama": "#downloadmenu",
        "count": 3
      },
      {
        "nama": "#menu",
        "count": 8
      },
      {
        "nama": "#cekpremium",
        "count": 4
      },
      {
        "nama": "#asupanmenu",
        "count": 2
      },
      {
        "nama": "#listpremium",
        "count": 5
      },
      {
        "nama": "#dashboard",
        "count": 2
      },
      {
        "nama": "#textpromenu",
        "count": 1
      },
      {
        "nama": "#logomenu",
        "count": 6
      },
      {
        "nama": "#lirik",
        "count": 1
      },
      {
        "nama": "#randommenu",
        "count": 1
      },
      {
        "nama": "#randomanime",
        "count": 3
      },
      {
        "nama": "#imageeffect",
        "count": 1
      },
      {
        "nama": "#cewekasiamenu",
        "count": 1
      },
      {
        "nama": "#sticker",
        "count": 27
      },
      {
        "nama": "#say",
        "count": 13
      },
      {
        "nama": "#attp",
        "count": 10
      },
      {
        "nama": "#donate",
        "count": 2
      },
      {
        "nama": "#infobot",
        "count": 1
      },
      {
        "nama": "#cekdrive",
        "count": 1
      },
      {
        "nama": "#cekbandwidth",
        "count": 1
      },
      {
        "nama": "#listsewa",
        "count": 7
      },
      {
        "nama": "#listbahasa",
        "count": 1
      },
      {
        "nama": "#convertmenu",
        "count": 1
      },
      {
        "nama": "#buygamelimit",
        "count": 1
      },
      {
        "nama": "#randomsticker",
        "count": 1
      },
      {
        "nama": "#storemenu",
        "count": 1
      }
    ]
  },
  {
    "jid": "6283896006942@s.whatsapp.net",
    "db": [
      {
        "nama": "#sticker",
        "count": 6
      },
      {
        "nama": "#smeme",
        "count": 12
      },
      {
        "nama": "#toimage",
        "count": 1
      },
      {
        "nama": "#afk",
        "count": 12
      },
      {
        "nama": "#allmenu",
        "count": 1
      }
    ]
  },
  {
    "jid": "6285774310331@s.whatsapp.net",
    "db": [
      {
        "nama": "#afk",
        "count": 7
      },
      {
        "nama": "#toimage",
        "count": 2
      },
      {
        "nama": "#menu",
        "count": 1
      },
      {
        "nama": "#allmenu",
        "count": 1
      },
      {
        "nama": "#sticker",
        "count": 1
      },
      {
        "nama": "#emojimix",
        "count": 1
      }
    ]
  },
  {
    "jid": "6281290161507@s.whatsapp.net",
    "db": [
      {
        "nama": "#sticker",
        "count": 2
      },
      {
        "nama": "#menu",
        "count": 1
      }
    ]
  },
  {
    "jid": "6285765329114@s.whatsapp.net",
    "db": [
      {
        "nama": "#sticker",
        "count": 1
      },
      {
        "nama": "#buylimit",
        "count": 1
      },
      {
        "nama": "#afk",
        "count": 2
      },
      {
        "nama": "#allmenu",
        "count": 1
      },
      {
        "nama": "#menu",
        "count": 1
      }
    ]
  },
  {
    "jid": "6287748984585@s.whatsapp.net",
    "db": [
      {
        "nama": "#afk",
        "count": 14
      },
      {
        "nama": "#emojimix",
        "count": 2
      },
      {
        "nama": "#say",
        "count": 2
      },
      {
        "nama": "#menu",
        "count": 4
      },
      {
        "nama": "#stalkingmenu",
        "count": 1
      },
      {
        "nama": "#sticker",
        "count": 9
      },
      {
        "nama": "#cowokasiamenu",
        "count": 1
      },
      {
        "nama": "#buylimit",
        "count": 4
      },
      {
        "nama": "#transfer",
        "count": 6
      },
      {
        "nama": "#smeme",
        "count": 4
      },
      {
        "nama": "#cogan",
        "count": 1
      },
      {
        "nama": "#groupmenu",
        "count": 2
      },
      {
        "nama": "#listpremium",
        "count": 1
      },
      {
        "nama": "#waifu",
        "count": 1
      },
      {
        "nama": "#casino",
        "count": 1
      },
      {
        "nama": "#buygamelimit",
        "count": 1
      },
      {
        "nama": "#photooxymenu",
        "count": 1
      },
      {
        "nama": "#funmenu",
        "count": 1
      },
      {
        "nama": "#nuliskanan",
        "count": 1
      },
      {
        "nama": "#nuliskiri",
        "count": 2
      },
      {
        "nama": "#allmenu",
        "count": 2
      },
      {
        "nama": "#storagemenu",
        "count": 1
      },
      {
        "nama": "#rpgmenu",
        "count": 1
      },
      {
        "nama": "#tes",
        "count": 1
      }
    ]
  },
  {
    "jid": "6283861171923@s.whatsapp.net",
    "db": [
      {
        "nama": "#menu",
        "count": 5
      },
      {
        "nama": "#downloadmenu",
        "count": 1
      },
      {
        "nama": "#allmenu",
        "count": 1
      },
      {
        "nama": "#randomanime",
        "count": 1
      },
      {
        "nama": "#afk",
        "count": 1
      },
      {
        "nama": "#tomp3",
        "count": 6
      }
    ]
  },
  {
    "jid": "60179255231@s.whatsapp.net",
    "db": [
      {
        "nama": "#smeme",
        "count": 4
      },
      {
        "nama": "#afk",
        "count": 8
      },
      {
        "nama": "#sticker",
        "count": 9
      },
      {
        "nama": "#tes",
        "count": 1
      }
    ]
  },
  {
    "jid": "6287815563188@s.whatsapp.net",
    "db": [
      {
        "nama": "#afk",
        "count": 4
      }
    ]
  },
  {
    "jid": "6281265815585@s.whatsapp.net",
    "db": [
      {
        "nama": "#afk",
        "count": 2
      }
    ]
  },
  {
    "jid": "6281342984911@s.whatsapp.net",
    "db": [
      {
        "nama": "#sticker",
        "count": 2
      },
      {
        "nama": "#menu",
        "count": 1
      }
    ]
  },
  {
    "jid": "628974131314@s.whatsapp.net",
    "db": [
      {
        "nama": "#menu",
        "count": 1
      },
      {
        "nama": "#allmenu",
        "count": 2
      }
    ]
  },
  {
    "jid": "6285701203115@s.whatsapp.net",
    "db": [
      {
        "nama": "#sticker",
        "count": 2
      },
      {
        "nama": "#afk",
        "count": 3
      },
      {
        "nama": "#tes",
        "count": 7
      },
      {
        "nama": "#menu",
        "count": 2
      },
      {
        "nama": "#rpgmenu",
        "count": 1
      },
      {
        "nama": "#nikah",
        "count": 1
      }
    ]
  },
  {
    "jid": "6285848768281@s.whatsapp.net",
    "db": [
      {
        "nama": "#sticker",
        "count": 1
      }
    ]
  },
  {
    "jid": "62882006284963@s.whatsapp.net",
    "db": [
      {
        "nama": "#menu",
        "count": 1
      },
      {
        "nama": "#ownermenu",
        "count": 1
      }
    ]
  },
  {
    "jid": "6281379455829@s.whatsapp.net",
    "db": [
      {
        "nama": "#afk",
        "count": 1
      },
      {
        "nama": "#tes",
        "count": 1
      },
      {
        "nama": "#allmenu",
        "count": 1
      }
    ]
  },
  {
    "jid": "6281361494940@s.whatsapp.net",
    "db": [
      {
        "nama": "#allmenu",
        "count": 2
      },
      {
        "nama": "#menu",
        "count": 2
      },
      {
        "nama": "#dashboard",
        "count": 1
      },
      {
        "nama": "#mainmenu",
        "count": 1
      },
      {
        "nama": "#transfer",
        "count": 1
      },
      {
        "nama": "#listpremium",
        "count": 1
      },
      {
        "nama": "#balancemenu",
        "count": 1
      },
      {
        "nama": "#listbahasa",
        "count": 1
      },
      {
        "nama": "#infobot",
        "count": 1
      }
    ]
  },
  {
    "jid": "6282188252967@s.whatsapp.net",
    "db": [
      {
        "nama": "#allmenu",
        "count": 2
      },
      {
        "nama": "#casino",
        "count": 2
      },
      {
        "nama": "#transfer",
        "count": 2
      },
      {
        "nama": "#stickerwm",
        "count": 6
      },
      {
        "nama": "#menu",
        "count": 1
      },
      {
        "nama": "#balancemenu",
        "count": 1
      },
      {
        "nama": "#sticker",
        "count": 1
      }
    ]
  },
  {
    "jid": "6285789063611@s.whatsapp.net",
    "db": [
      {
        "nama": "#sticker",
        "count": 1
      }
    ]
  },
  {
    "jid": "6281225611196@s.whatsapp.net",
    "db": [
      {
        "nama": "#menu",
        "count": 8
      },
      {
        "nama": "#sticker",
        "count": 7
      },
      {
        "nama": "#smeme",
        "count": 10
      },
      {
        "nama": "#toimage",
        "count": 1
      }
    ]
  },
  {
    "jid": "6289510501420@s.whatsapp.net",
    "db": [
      {
        "nama": "#menu",
        "count": 1
      },
      {
        "nama": "#logomenu",
        "count": 1
      },
      {
        "nama": "#afk",
        "count": 2
      }
    ]
  },
  {
    "jid": "6285642907596@s.whatsapp.net",
    "db": [
      {
        "nama": "#afk",
        "count": 12
      },
      {
        "nama": "#sticker",
        "count": 1
      }
    ]
  },
  {
    "jid": "6283150320677@s.whatsapp.net",
    "db": [
      {
        "nama": "#allmenu",
        "count": 1
      }
    ]
  },
  {
    "jid": "62895708780200@s.whatsapp.net",
    "db": [
      {
        "nama": "#menu",
        "count": 2
      }
    ]
  },
  {
    "jid": "6283133598722@s.whatsapp.net",
    "db": [
      {
        "nama": "#welcome",
        "count": 2
      },
      {
        "nama": "#menu",
        "count": 1
      }
    ]
  },
  {
    "jid": "6281310226566@s.whatsapp.net",
    "db": [
      {
        "nama": "#menu",
        "count": 2
      },
      {
        "nama": "#allmenu",
        "count": 1
      }
    ]
  },
  {
    "jid": "6283852886383@s.whatsapp.net",
    "db": [
      {
        "nama": "#menu",
        "count": 2
      },
      {
        "nama": "#cowokasiamenu",
        "count": 1
      }
    ]
  },
  {
    "jid": "6287717630726@s.whatsapp.net",
    "db": [
      {
        "nama": "#menu",
        "count": 1
      }
    ]
  },
  {
    "jid": "6281314328414@s.whatsapp.net",
    "db": [
      {
        "nama": "#menu",
        "count": 1
      },
      {
        "nama": "#sticker",
        "count": 2
      }
    ]
  },
  {
    "jid": "6281586815020@s.whatsapp.net",
    "db": [
      {
        "nama": "#sticker",
        "count": 1
      }
    ]
  },
  {
    "jid": "62895341199012@s.whatsapp.net",
    "db": [
      {
        "nama": "#sticker",
        "count": 1
      }
    ]
  },
  {
    "jid": "6283832733067@s.whatsapp.net",
    "db": [
      {
        "nama": "#menu",
        "count": 2
      },
      {
        "nama": "#sticker",
        "count": 3
      },
      {
        "nama": "#toimage",
        "count": 2
      },
      {
        "nama": "#allmenu",
        "count": 1
      }
    ]
  },
  {
    "jid": "6285731600190@s.whatsapp.net",
    "db": [
      {
        "nama": "#menu",
        "count": 5
      },
      {
        "nama": "#afk",
        "count": 1
      },
      {
        "nama": "#sticker",
        "count": 1
      }
    ]
  },
  {
    "jid": "62882008654015@s.whatsapp.net",
    "db": [
      {
        "nama": "#menu",
        "count": 5
      },
      {
        "nama": "#allmenu",
        "count": 7
      },
      {
        "nama": "#smeme",
        "count": 14
      },
      {
        "nama": "#logomenu",
        "count": 1
      },
      {
        "nama": "#buylimit",
        "count": 32
      },
      {
        "nama": "#gamemenu",
        "count": 2
      },
      {
        "nama": "#transfer",
        "count": 7
      },
      {
        "nama": "#rpgmenu",
        "count": 2
      },
      {
        "nama": "#afk",
        "count": 8
      },
      {
        "nama": "#buygamelimit",
        "count": 1
      }
    ]
  },
  {
    "jid": "6283180217624@s.whatsapp.net",
    "db": [
      {
        "nama": "#menu",
        "count": 1
      }
    ]
  },
  {
    "jid": "6285326871215@s.whatsapp.net",
    "db": [
      {
        "nama": "#tes",
        "count": 3
      },
      {
        "nama": "#allmenu",
        "count": 1
      },
      {
        "nama": "#randomanime",
        "count": 2
      },
      {
        "nama": "#anonymousmenu",
        "count": 1
      }
    ]
  },
  {
    "jid": "62895327242884@s.whatsapp.net",
    "db": [
      {
        "nama": "#menu",
        "count": 1
      },
      {
        "nama": "#allmenu",
        "count": 3
      },
      {
        "nama": "#transfer",
        "count": 3
      },
      {
        "nama": "#buylimit",
        "count": 1
      },
      {
        "nama": "#buygamelimit",
        "count": 1
      },
      {
        "nama": "#nsfwmenu",
        "count": 1
      },
      {
        "nama": "#sticker",
        "count": 1
      },
      {
        "nama": "#afk",
        "count": 2
      }
    ]
  },
  {
    "jid": "6283110640088@s.whatsapp.net",
    "db": [
      {
        "nama": "#menu",
        "count": 1
      },
      {
        "nama": "#welcome",
        "count": 1
      }
    ]
  },
  {
    "jid": "6283861984249@s.whatsapp.net",
    "db": [
      {
        "nama": "#menu",
        "count": 2
      },
      {
        "nama": "#allmenu",
        "count": 2
      },
      {
        "nama": "#close",
        "count": 5
      },
      {
        "nama": "#group",
        "count": 6
      },
      {
        "nama": "#antilink",
        "count": 3
      }
    ]
  },
  {
    "jid": "62895411404005@s.whatsapp.net",
    "db": [
      {
        "nama": "#menu",
        "count": 1
      }
    ]
  },
  {
    "jid": "6281249864586@s.whatsapp.net",
    "db": [
      {
        "nama": "#sticker",
        "count": 4
      },
      {
        "nama": "#afk",
        "count": 2
      }
    ]
  },
  {
    "jid": "6283190885818@s.whatsapp.net",
    "db": [
      {
        "nama": "#menu",
        "count": 1
      }
    ]
  },
  {
    "jid": "6283873190084@s.whatsapp.net",
    "db": [
      {
        "nama": "#logomenu",
        "count": 1
      },
      {
        "nama": "#close",
        "count": 5
      },
      {
        "nama": "#group",
        "count": 3
      }
    ]
  },
  {
    "jid": "6282220521236@s.whatsapp.net",
    "db": [
      {
        "nama": "#menu",
        "count": 1
      }
    ]
  },
  {
    "jid": "6285955234173@s.whatsapp.net",
    "db": [
      {
        "nama": "#afk",
        "count": 2
      },
      {
        "nama": "#sticker",
        "count": 1
      },
      {
        "nama": "#tes",
        "count": 2
      }
    ]
  },
  {
    "jid": "62895339088979@s.whatsapp.net",
    "db": [
      {
        "nama": "#menu",
        "count": 1
      },
      {
        "nama": "#voicechanger",
        "count": 1
      },
      {
        "nama": "#allmenu",
        "count": 2
      },
      {
        "nama": "#tes",
        "count": 1
      }
    ]
  },
  {
    "jid": "6285267158583@s.whatsapp.net",
    "db": [
      {
        "nama": "#sticker",
        "count": 1
      },
      {
        "nama": "#menu",
        "count": 1
      },
      {
        "nama": "#logomenu",
        "count": 1
      }
    ]
  },
  {
    "jid": "6287899922608@s.whatsapp.net",
    "db": [
      {
        "nama": "#sticker",
        "count": 3
      },
      {
        "nama": "#allmenu",
        "count": 3
      },
      {
        "nama": "#menu",
        "count": 2
      },
      {
        "nama": "#searchmenu",
        "count": 1
      },
      {
        "nama": "#downloadmenu",
        "count": 1
      },
      {
        "nama": "#mediafire",
        "count": 1
      },
      {
        "nama": "#groupmenu",
        "count": 1
      },
      {
        "nama": "#listpremium",
        "count": 1
      },
      {
        "nama": "#donate",
        "count": 1
      }
    ]
  },
  {
    "jid": "6282138166200@s.whatsapp.net",
    "db": [
      {
        "nama": "#menu",
        "count": 1
      },
      {
        "nama": "#logomenu",
        "count": 1
      },
      {
        "nama": "#allmenu",
        "count": 1
      },
      {
        "nama": "#downloadmenu",
        "count": 1
      }
    ]
  },
  {
    "jid": "6287831757289@s.whatsapp.net",
    "db": [
      {
        "nama": "#tes",
        "count": 3
      },
      {
        "nama": "#afk",
        "count": 1
      },
      {
        "nama": "#mediafire",
        "count": 2
      },
      {
        "nama": "#welcome",
        "count": 2
      },
      {
        "nama": "#menu",
        "count": 2
      },
      {
        "nama": "#antilink",
        "count": 1
      },
      {
        "nama": "#tovn",
        "count": 1
      }
    ]
  },
  {
    "jid": "6287792327042@s.whatsapp.net",
    "db": [
      {
        "nama": "#menu",
        "count": 1
      },
      {
        "nama": "#allmenu",
        "count": 1
      }
    ]
  },
  {
    "jid": "6285738835129@s.whatsapp.net",
    "db": [
      {
        "nama": "#afk",
        "count": 1
      },
      {
        "nama": "#gamemenu",
        "count": 3
      },
      {
        "nama": "#buylimit",
        "count": 1
      },
      {
        "nama": "#emojimix",
        "count": 1
      },
      {
        "nama": "#tes",
        "count": 2
      },
      {
        "nama": "#menu",
        "count": 1
      },
      {
        "nama": "#downloadmenu",
        "count": 1
      },
      {
        "nama": "#tovn",
        "count": 1
      },
      {
        "nama": "#allmenu",
        "count": 1
      },
      {
        "nama": "#nuliskiri",
        "count": 1
      }
    ]
  },
  {
    "jid": "6281585627589@s.whatsapp.net",
    "db": [
      {
        "nama": "#group",
        "count": 1
      }
    ]
  },
  {
    "jid": "6287790394179@s.whatsapp.net",
    "db": [
      {
        "nama": "#group",
        "count": 6
      },
      {
        "nama": "#mute",
        "count": 9
      },
      {
        "nama": "#afk",
        "count": 6
      },
      {
        "nama": "#tes",
        "count": 19
      },
      {
        "nama": "#resetlimit",
        "count": 2
      },
      {
        "nama": "#sticker",
        "count": 7
      },
      {
        "nama": "#close",
        "count": 5
      },
      {
        "nama": "#menu",
        "count": 14
      },
      {
        "nama": "#groupmenu",
        "count": 1
      },
      {
        "nama": "#infobot",
        "count": 1
      },
      {
        "nama": "#revoke",
        "count": 1
      },
      {
        "nama": "#mediafire",
        "count": 2
      },
      {
        "nama": "#ownermenu",
        "count": 1
      },
      {
        "nama": "#toimage",
        "count": 2
      },
      {
        "nama": "#tomp3",
        "count": 2
      },
      {
        "nama": "#allmenu",
        "count": 1
      }
    ]
  },
  {
    "jid": "6281243963688@s.whatsapp.net",
    "db": [
      {
        "nama": "#menu",
        "count": 1
      }
    ]
  },
  {
    "jid": "6281548104237@s.whatsapp.net",
    "db": [
      {
        "nama": "#sticker",
        "count": 3
      },
      {
        "nama": "#allmenu",
        "count": 1
      }
    ]
  },
  {
    "jid": "6285780034080@s.whatsapp.net",
    "db": [
      {
        "nama": "#menu",
        "count": 8
      }
    ]
  },
  {
    "jid": "6287785153249@s.whatsapp.net",
    "db": [
      {
        "nama": "#tes",
        "count": 2
      },
      {
        "nama": "#allmenu",
        "count": 4
      },
      {
        "nama": "#menu",
        "count": 1
      },
      {
        "nama": "#sticker",
        "count": 4
      }
    ]
  },
  {
    "jid": "6283150361100@s.whatsapp.net",
    "db": [
      {
        "nama": "#menu",
        "count": 1
      },
      {
        "nama": "#allmenu",
        "count": 1
      },
      {
        "nama": "#sticker",
        "count": 1
      },
      {
        "nama": "#stickerwm",
        "count": 1
      }
    ]
  },
  {
    "jid": "6285366062784@s.whatsapp.net",
    "db": [
      {
        "nama": "#tes",
        "count": 1
      },
      {
        "nama": "#afk",
        "count": 3
      },
      {
        "nama": "#toimage",
        "count": 2
      },
      {
        "nama": "#sticker",
        "count": 2
      }
    ]
  },
  {
    "jid": "6281244612204@s.whatsapp.net",
    "db": [
      {
        "nama": "#allmenu",
        "count": 1
      }
    ]
  },
  {
    "jid": "6281456023597@s.whatsapp.net",
    "db": [
      {
        "nama": "#menu",
        "count": 1
      },
      {
        "nama": "#allmenu",
        "count": 1
      }
    ]
  },
  {
    "jid": "6283831981129@s.whatsapp.net",
    "db": [
      {
        "nama": "#menu",
        "count": 1
      }
    ]
  },
  {
    "jid": "6283869052250@s.whatsapp.net",
    "db": [
      {
        "nama": "#close",
        "count": 1
      },
      {
        "nama": "#tes",
        "count": 2
      },
      {
        "nama": "#group",
        "count": 1
      },
      {
        "nama": "#sticker",
        "count": 1
      },
      {
        "nama": "#addprem",
        "count": 6
      },
      {
        "nama": "#cekpremium",
        "count": 1
      },
      {
        "nama": "#emojimix",
        "count": 4
      },
      {
        "nama": "#say",
        "count": 2
      },
      {
        "nama": "#menu",
        "count": 1
      }
    ]
  },
  {
    "jid": "6283861724688@s.whatsapp.net",
    "db": [
      {
        "nama": "#mediafire",
        "count": 2
      },
      {
        "nama": "#tovn",
        "count": 2
      },
      {
        "nama": "#listpremium",
        "count": 1
      }
    ]
  },
  {
    "jid": "62881010625639@s.whatsapp.net",
    "db": [
      {
        "nama": "#left",
        "count": 1
      },
      {
        "nama": "#menu",
        "count": 1
      },
      {
        "nama": "#allmenu",
        "count": 1
      }
    ]
  },
  {
    "jid": "6287842553124@s.whatsapp.net",
    "db": [
      {
        "nama": "#allmenu",
        "count": 1
      }
    ]
  },
  {
    "jid": "6287776663524@s.whatsapp.net",
    "db": [
      {
        "nama": "#menu",
        "count": 1
      },
      {
        "nama": "#allmenu",
        "count": 1
      },
      {
        "nama": "#storemenu",
        "count": 1
      }
    ]
  },
  {
    "jid": "6289661510200@s.whatsapp.net",
    "db": [
      {
        "nama": "#menu",
        "count": 2
      },
      {
        "nama": "#mainmenu",
        "count": 1
      },
      {
        "nama": "#sticker",
        "count": 1
      },
      {
        "nama": "#infobot",
        "count": 1
      }
    ]
  },
  {
    "jid": "6282160657000@s.whatsapp.net",
    "db": [
      {
        "nama": "#menu",
        "count": 3
      },
      {
        "nama": "#allmenu",
        "count": 2
      },
      {
        "nama": "#sticker",
        "count": 1
      },
      {
        "nama": "#toimage",
        "count": 1
      }
    ]
  },
  {
    "jid": "6281282167290@s.whatsapp.net",
    "db": [
      {
        "nama": "#cewekasiamenu",
        "count": 1
      },
      {
        "nama": "#nsfwmenu",
        "count": 1
      },
      {
        "nama": "#cowokasiamenu",
        "count": 1
      }
    ]
  },
  {
    "jid": "6282192906119@s.whatsapp.net",
    "db": [
      {
        "nama": "#menu",
        "count": 1
      }
    ]
  },
  {
    "jid": "6282260654188@s.whatsapp.net",
    "db": [
      {
        "nama": "#menu",
        "count": 3
      },
      {
        "nama": "#asupanmenu",
        "count": 1
      },
      {
        "nama": "#nsfwmenu",
        "count": 1
      }
    ]
  },
  {
    "jid": "6281398499199@s.whatsapp.net",
    "db": [
      {
        "nama": "#menu",
        "count": 1
      },
      {
        "nama": "#asupanmenu",
        "count": 1
      }
    ]
  },
  {
    "jid": "6281262280270@s.whatsapp.net",
    "db": [
      {
        "nama": "#menu",
        "count": 2
      },
      {
        "nama": "#rpgmenu",
        "count": 1
      }
    ]
  },
  {
    "jid": "6282267898168@s.whatsapp.net",
    "db": [
      {
        "nama": "#menu",
        "count": 2
      },
      {
        "nama": "#allmenu",
        "count": 2
      }
    ]
  },
  {
    "jid": "6282117100926@s.whatsapp.net",
    "db": [
      {
        "nama": "#menu",
        "count": 2
      },
      {
        "nama": "#nsfwmenu",
        "count": 1
      },
      {
        "nama": "#asupanmenu",
        "count": 1
      },
      {
        "nama": "#allmenu",
        "count": 2
      }
    ]
  },
  {
    "jid": "6287854525961@s.whatsapp.net",
    "db": [
      {
        "nama": "#menu",
        "count": 1
      },
      {
        "nama": "#logomenu",
        "count": 1
      }
    ]
  },
  {
    "jid": "62895411515040@s.whatsapp.net",
    "db": [
      {
        "nama": "#menu",
        "count": 1
      },
      {
        "nama": "#mainmenu",
        "count": 1
      }
    ]
  },
  {
    "jid": "6282137866911@s.whatsapp.net",
    "db": [
      {
        "nama": "#menu",
        "count": 1
      }
    ]
  },
  {
    "jid": "62858194591762@s.whatsapp.net",
    "db": [
      {
        "nama": "#tes",
        "count": 4
      },
      {
        "nama": "#afk",
        "count": 2
      },
      {
        "nama": "#casino",
        "count": 1
      }
    ]
  },
  {
    "jid": "6285854371920@s.whatsapp.net",
    "db": [
      {
        "nama": "#menu",
        "count": 1
      },
      {
        "nama": "#allmenu",
        "count": 1
      }
    ]
  },
  {
    "jid": "6287742210569@s.whatsapp.net",
    "db": [
      {
        "nama": "#menu",
        "count": 1
      },
      {
        "nama": "#allmenu",
        "count": 1
      }
    ]
  },
  {
    "jid": "6282129871988@s.whatsapp.net",
    "db": [
      {
        "nama": "#antilink",
        "count": 2
      }
    ]
  },
  {
    "jid": "6283876003588@s.whatsapp.net",
    "db": [
      {
        "nama": "#menu",
        "count": 1
      }
    ]
  },
  {
    "jid": "6281320165933@s.whatsapp.net",
    "db": [
      {
        "nama": "#menu",
        "count": 1
      },
      {
        "nama": "#downloadmenu",
        "count": 2
      },
      {
        "nama": "#allmenu",
        "count": 3
      },
      {
        "nama": "#tomp3",
        "count": 3
      }
    ]
  },
  {
    "jid": "60167117123@s.whatsapp.net",
    "db": [
      {
        "nama": "#menu",
        "count": 2
      }
    ]
  },
  {
    "jid": "62814667228784@s.whatsapp.net",
    "db": [
      {
        "nama": "#menu",
        "count": 2
      },
      {
        "nama": "#nsfwmenu",
        "count": 2
      },
      {
        "nama": "#allmenu",
        "count": 1
      }
    ]
  },
  {
    "jid": "6283870657080@s.whatsapp.net",
    "db": [
      {
        "nama": "#tes",
        "count": 4
      },
      {
        "nama": "#menu",
        "count": 6
      },
      {
        "nama": "#listpremium",
        "count": 1
      },
      {
        "nama": "#addprem",
        "count": 1
      },
      {
        "nama": "#downloadmenu",
        "count": 1
      }
    ]
  },
  {
    "jid": "6281770412934@s.whatsapp.net",
    "db": [
      {
        "nama": "#tes",
        "count": 1
      }
    ]
  },
  {
    "jid": "6283139046586@s.whatsapp.net",
    "db": [
      {
        "nama": "#menu",
        "count": 1
      }
    ]
  },
  {
    "jid": "6281775165315@s.whatsapp.net",
    "db": [
      {
        "nama": "#resetlimit",
        "count": 1
      },
      {
        "nama": "#tes",
        "count": 88
      },
      {
        "nama": "#menu",
        "count": 43
      },
      {
        "nama": "#addprem",
        "count": 1
      },
      {
        "nama": "#toimage",
        "count": 10
      },
      {
        "nama": "#allmenu",
        "count": 2
      },
      {
        "nama": "#sticker",
        "count": 9
      },
      {
        "nama": "#afk",
        "count": 5
      },
      {
        "nama": "#stickerwm",
        "count": 1
      },
      {
        "nama": "#close",
        "count": 2
      },
      {
        "nama": "#nikah",
        "count": 31
      },
      {
        "nama": "#casino",
        "count": 1
      },
      {
        "nama": "#delcasino",
        "count": 1
      },
      {
        "nama": "#attp",
        "count": 2
      },
      {
        "nama": "#group",
        "count": 2
      },
      {
        "nama": "#cerai",
        "count": 3
      },
      {
        "nama": "#downloadmenu",
        "count": 4
      },
      {
        "nama": "#infobot",
        "count": 1
      },
      {
        "nama": "#mute",
        "count": 1
      }
    ]
  },
  {
    "jid": "6288263864653@s.whatsapp.net",
    "db": [
      {
        "nama": "#menu",
        "count": 1
      }
    ]
  },
  {
    "jid": "6282122843831@s.whatsapp.net",
    "db": [
      {
        "nama": "#tes",
        "count": 2
      },
      {
        "nama": "#sticker",
        "count": 1
      }
    ]
  },
  {
    "jid": "6285838733984@s.whatsapp.net",
    "db": [
      {
        "nama": "#afk",
        "count": 10
      }
    ]
  },
  {
    "jid": "6285925703182@s.whatsapp.net",
    "db": [
      {
        "nama": "#menu",
        "count": 6
      },
      {
        "nama": "#mainmenu",
        "count": 1
      },
      {
        "nama": "#randomsticker",
        "count": 1
      },
      {
        "nama": "#listbahasa",
        "count": 1
      },
      {
        "nama": "#donate",
        "count": 1
      },
      {
        "nama": "#afk",
        "count": 1
      },
      {
        "nama": "#downloadmenu",
        "count": 1
      }
    ]
  },
  {
    "jid": "6282348253130@s.whatsapp.net",
    "db": [
      {
        "nama": "#buylimit",
        "count": 1
      }
    ]
  },
  {
    "jid": "6283110568884@s.whatsapp.net",
    "db": [
      {
        "nama": "#menu",
        "count": 1
      }
    ]
  },
  {
    "jid": "6283837740559@s.whatsapp.net",
    "db": [
      {
        "nama": "#afk",
        "count": 3
      }
    ]
  },
  {
    "jid": "6281247904596@s.whatsapp.net",
    "db": [
      {
        "nama": "#allmenu",
        "count": 1
      }
    ]
  }
]